logiklib/__init__.py
logiklib/zeroasic/z1000/README.md
logiklib/zeroasic/z1000/z1000.py
logiklib/zeroasic/z1002/README.md
logiklib/zeroasic/z1002/z1002.py
logiklib/zeroasic/z1010/README.md
logiklib/zeroasic/z1010/z1010.py
logiklib/zeroasic/z1012/README.md
logiklib/zeroasic/z1012/z1012.py
logiklib/zeroasic/z1060/README.md
logiklib/zeroasic/z1060/z1060.py
logiklib/zeroasic/z1062/README.md
logiklib/zeroasic/z1062/z1062.py
logiklib-0.2.0.dist-info/licenses/LICENSE
logiklib-0.2.0.dist-info/METADATA
logiklib-0.2.0.dist-info/WHEEL
logiklib-0.2.0.dist-info/top_level.txt
logiklib-0.2.0.dist-info/RECORD
