Metadata-Version: 2.4
Name: logiklib
Version: 0.2.0
Summary: Library of FPGA architectures
Author: Zero ASIC
License:                                  Apache License
Project-URL: Homepage, https://github.com/siliconcompiler/logiklib.git
Requires-Python: >=3.8
License-File: LICENSE
Requires-Dist: siliconcompiler>=0.35.1
Provides-Extra: test
Requires-Dist: pytest==8.4.2; extra == "test"
Requires-Dist: flake8==7.3.0; extra == "test"
Requires-Dist: codespell==2.4.1; extra == "test"
Dynamic: license-file
